ibot
