Metadata-Version: 1.1
Name: ibot
Version: 0.1.1
Summary: a bot
Home-page: https://github.com/wwj718/ibot
Author: wenjie wu
Author-email: wuwenjie718@gmail.com
License: MIT license
Keywords: ibot
Platform: UNKNOWN
Classifier: Development Status :: 2 - Pre-Alpha
Classifier: Intended Audience :: Developers
Classifier: License :: OSI Approved :: MIT License
Classifier: Natural Language :: English
Classifier: Programming Language :: Python :: 2
Classifier: Programming Language :: Python :: 2.6
Classifier: Programming Language :: Python :: 2.7
Classifier: Programming Language :: Python :: 3
Classifier: Programming Language :: Python :: 3.3
Classifier: Programming Language :: Python :: 3.4
Classifier: Programming Language :: Python :: 3.5
